hfexcel/__init__.py
hfexcel/helpers.py
hfexcel/managers.py
hfexcel/models.py
hfexcel/schemas.py
hfexcel/styles.py
hfexcel/utils.py
hfexcel-0.0.17.dist-info/LICENSE
hfexcel-0.0.17.dist-info/METADATA
hfexcel-0.0.17.dist-info/WHEEL
hfexcel-0.0.17.dist-info/top_level.txt
hfexcel-0.0.17.dist-info/RECORD
