Metadata-Version: 2.1
Name: hfexcel
Version: 0.0.17
Summary: human friendly excel creation in python
Home-page: https://github.com/ebsaral/hfexcel
Author: Emin Bugra Saral
Author-email: eminbugrasaral@me.com
License: BSD
Project-URL: Documentation, https://github.com/ebsaral/hfexcel
Project-URL: Funding, https://github.com/ebsaral/hfexcel
Project-URL: Source, https://github.com/ebsaral/hfexcel
Keywords: xlsxwriter xlsx excel json writing python wrapper
Platform: UNKNOWN
Classifier: License :: OSI Approved :: BSD License
Classifier: Operating System :: OS Independent
Classifier: Programming Language :: Python
Classifier: Programming Language :: Python :: 3
Classifier: Programming Language :: Python :: 3.6
Classifier: Programming Language :: Python :: 3.7
Classifier: Programming Language :: Python :: 3 :: Only
Classifier: Topic :: Internet :: WWW/HTTP
Classifier: Topic :: Internet :: WWW/HTTP :: Dynamic Content
Classifier: Topic :: Text Processing :: Linguistic
Classifier: Topic :: Software Development :: Libraries :: Python Modules
Requires-Dist: xlsxwriter
Requires-Dist: jsonschema (==2.6.0)
Requires-Dist: pytest
